framework_reproducibility-0.6.0.dist-info/DESCRIPTION.rst
framework_reproducibility-0.6.0.dist-info/METADATA
framework_reproducibility-0.6.0.dist-info/RECORD
framework_reproducibility-0.6.0.dist-info/WHEEL
framework_reproducibility-0.6.0.dist-info/metadata.json
framework_reproducibility-0.6.0.dist-info/top_level.txt
fwr13y/__init__.py
fwr13y/version.py
fwr13y/d9m/__init__.py
fwr13y/d9m/utils.py
fwr13y/d9m/tensorflow/__init__.py
fwr13y/d9m/tensorflow/enable_determinism.py
fwr13y/d9m/tensorflow/patch.py
fwr13y/d9m/tensorflow/patch_bias_add.py
fwr13y/d9m/tensorflow/patch_segment_sum.py
fwr13y/d9m/tensorflow/patch_unsorted_segment_sum.py
fwr13y/seeder/__init__.py
fwr13y/seeder/paddle.py
fwr13y/seeder/pyt.py
fwr13y/seeder/seed_gen.py
fwr13y/seeder/tf.py
